promptprep/__init__.py
promptprep/aggregator.py
promptprep/cli.py
promptprep/config.py
promptprep/formatters.py
promptprep/tui.py
promptprep-0.1.12.dist-info/licenses/LICENSE
promptprep-0.1.12.dist-info/METADATA
promptprep-0.1.12.dist-info/WHEEL
promptprep-0.1.12.dist-info/entry_points.txt
promptprep-0.1.12.dist-info/top_level.txt
promptprep-0.1.12.dist-info/RECORD
