Metadata-Version: 2.4
Name: promptprep
Version: 0.1.12
Summary: A code aggregator tool for consolidating code files into a single file with an ASCII directory tree.
Author-email: Kartik Mandar <kartik4321mandar@gmail.com>
License-Expression: MIT
Project-URL: Homepage, https://github.com/kartikmandar/promptprep
Project-URL: Bug Tracker, https://github.com/kartikmandar/promptprep/issues
Project-URL: Repository, https://github.com/kartikmandar/promptprep
Keywords: code,aggregator,prompt,llm,gpt,ai,context,cli,developer-tools
Classifier: Development Status :: 4 - Beta
Classifier: Environment :: Console
Classifier: Intended Audience :: Developers
Classifier: Programming Language :: Python :: 3
Classifier: Programming Language :: Python :: 3.10
Classifier: Programming Language :: Python :: 3.11
Classifier: Programming Language :: Python :: 3.12
Classifier: Operating System :: OS Independent
Classifier: Topic :: Software Development :: Libraries :: Python Modules
Classifier: Topic :: Software Development :: Documentation
Classifier: Topic :: Software Development :: Build Tools
Classifier: Topic :: Utilities
Classifier: Topic :: Text Processing
Requires-Python: >=3.10
License-File: LICENSE
Requires-Dist: tqdm
Requires-Dist: tiktoken
Provides-Extra: highlighting
Requires-Dist: pygments>=2.10.0; extra == "highlighting"
Provides-Extra: dev
Requires-Dist: pytest>=6.0; extra == "dev"
Requires-Dist: black>=22.0; extra == "dev"
Requires-Dist: ruff; extra == "dev"
Requires-Dist: build; extra == "dev"
Requires-Dist: twine; extra == "dev"
Requires-Dist: bump-my-version; extra == "dev"
Requires-Dist: pytest-cov; extra == "dev"
Requires-Dist: pytest-mock; extra == "dev"
Requires-Dist: pygments>=2.10.0; extra == "dev"
Requires-Dist: sphinx; extra == "dev"
Requires-Dist: sphinx-rtd-theme; extra == "dev"
Requires-Dist: myst-parser; extra == "dev"
Provides-Extra: docs
Requires-Dist: sphinx>=8.0; extra == "docs"
Requires-Dist: sphinx-rtd-theme; extra == "docs"
Requires-Dist: myst-parser; extra == "docs"
Provides-Extra: all
Requires-Dist: pygments>=2.10.0; extra == "all"
Dynamic: license-file
